ordinal_list/__init__.py
ordinal_list/utils.py
ordinal_list-0.2.0.dist-info/LICENSE
ordinal_list-0.2.0.dist-info/METADATA
ordinal_list-0.2.0.dist-info/WHEEL
ordinal_list-0.2.0.dist-info/top_level.txt
ordinal_list-0.2.0.dist-info/RECORD
