Metadata-Version: 2.1
Name: ordinal-list
Version: 0.2.0
Summary: A Python library that uses ordinal numbers to work with lists.
Author: Jimmy Jensen
License: The MIT License (MIT)
Project-URL: Repository, https://github.com/mrjsj/ordinal-list
Keywords: ordinal,list,indexing,python,0-based,1-based
Classifier: Programming Language :: Python :: 3
Classifier: Programming Language :: Python :: 3.8
Classifier: Programming Language :: Python :: 3.9
Classifier: Programming Language :: Python :: 3.10
Classifier: Programming Language :: Python :: 3.11
Classifier: Programming Language :: Python :: 3.12
Classifier: License :: OSI Approved :: MIT License
Classifier: Operating System :: OS Independent
Requires-Python: >=3.8
License-File: LICENSE
Provides-Extra: dev
Requires-Dist: pytest >=6.2.5 ; extra == 'dev'
